neo4pm/__init__.py
neo4pm/log_manager.py
neo4pm/common/__init__.py
neo4pm/common/identifiers.py
neo4pm/connection/__init__.py
neo4pm/connection/connection_manager.py
neo4pm/dfg/__init__.py
neo4pm/dfg/dfg_manager.py
neo4pm/importer/__init__.py
neo4pm/importer/batch/__init__.py
neo4pm/importer/batch/transformer.py
neo4pm/index/__init__.py
neo4pm/index/index_manager.py
neo4pm/transformer/__init__.py
neo4pm/transformer/batch/__init__.py
neo4pm/transformer/batch/ocel/__init__.py
neo4pm/transformer/batch/ocel/lpg2ocel.py
neo4pm-1.0.2.dist-info/METADATA
neo4pm-1.0.2.dist-info/WHEEL
neo4pm-1.0.2.dist-info/top_level.txt
neo4pm-1.0.2.dist-info/RECORD
