Metadata-Version: 2.1
Name: neo4pm
Version: 1.0.2
Summary: Python neo4pm Package
Home-page: UNKNOWN
Author: UNKNOWN
Author-email: UNKNOWN
License: UNKNOWN
Platform: UNKNOWN
Requires-Dist: pandas
Requires-Dist: numpy
Requires-Dist: datetime
Requires-Dist: py2neo
